qrm545_xd/Option.py
qrm545_xd/VaR.py
qrm545_xd/__init__.py
qrm545_xd/calculation.py
qrm545_xd/cov_matrix.py
qrm545_xd/linear_regression.py
qrm545_xd/optimal_portfolio.py
qrm545_xd/risk_attribution.py
qrm545_xd/risk_parity.py
qrm545_xd/simulation.py
rm545_xd-0.7.2.dist-info/METADATA
rm545_xd-0.7.2.dist-info/WHEEL
rm545_xd-0.7.2.dist-info/top_level.txt
rm545_xd-0.7.2.dist-info/RECORD
