Metadata-Version: 2.1
Name: rm545-xd
Version: 0.7.2
Summary: use for Quant545
Author-email: Xuanting Dong <xd67@duke.edu>
Classifier: Programming Language :: Python :: 3
Classifier: License :: OSI Approved :: MIT License
Classifier: Operating System :: OS Independent
Requires-Python: >=3.7
